pyunormalize/__init__.py
pyunormalize/_version.py
pyunormalize/normalization.py
pyunormalize/unicode.py
pyunormalize/test/__init__.py
pyunormalize/test/test_pyunormalize.py
pyunormalize/test/unicode_conformance.py
pyunormalize/test/data/NormalizationTest.txt
pyunormalize_micropip-15.1.0.dist-info/LICENSE
pyunormalize_micropip-15.1.0.dist-info/METADATA
pyunormalize_micropip-15.1.0.dist-info/WHEEL
pyunormalize_micropip-15.1.0.dist-info/top_level.txt
pyunormalize_micropip-15.1.0.dist-info/RECORD
