Metadata-Version: 2.1
Name: pyunormalize-micropip
Version: 15.1.0
Summary: Unicode normalization forms (NFC, NFKC, NFD, NFKD). A library independent from the Python core Unicode database.
Home-page: https://github.com/mlodewijck/pyunormalize
Author: Marc Lodewijck
Author-email: mlodewijck@gmail.com
License: MIT
Project-URL: Bug Reports, https://github.com/mlodewijck/pyunormalize/issues
Project-URL: Source, https://github.com/mlodewijck/pyunormalize/
Keywords: Unicode,Unicode data,Unicode normalization,normalization,NFC,NFD,NFKC,NFKD,Unicode Normalization Forms,Canonical Ordering Algorithm,Canonical Composition Algorithm,canonical ordering,canonical composition,Hangul Syllable Composition Algorithm,Hangul Syllable Decomposition Algorithm,Hangul syllables,Hangul jamo characters
Classifier: Intended Audience :: Developers
Classifier: License :: OSI Approved :: MIT License
Classifier: Programming Language :: Python :: 3.6
Classifier: Programming Language :: Python :: 3.7
Classifier: Programming Language :: Python :: 3.8
Classifier: Programming Language :: Python :: 3.9
Classifier: Programming Language :: Python :: 3.10
Classifier: Programming Language :: Python :: 3.11
Classifier: Topic :: Software Development
Classifier: Topic :: Software Development :: Internationalization
Classifier: Topic :: Text Processing
Classifier: Topic :: Text Processing :: Linguistic
Classifier: Topic :: Utilities
Requires-Python: >=3.6
License-File: LICENSE
